lazyxml/__init__.py
lazyxml/builder.py
lazyxml/consts.py
lazyxml/parser.py
lazyxml/utils.py
lazyxml-1.3.2.dist-info/LICENSE
lazyxml-1.3.2.dist-info/METADATA
lazyxml-1.3.2.dist-info/WHEEL
lazyxml-1.3.2.dist-info/top_level.txt
lazyxml-1.3.2.dist-info/RECORD
