Metadata-Version: 2.1
Name: lazyxml
Version: 1.3.2
Summary: A simple xml parse and build library.
Home-page: https://github.com/druagoon/lazyxml
Author: Zonglong Fan
Author-email: <lazyboy.fan@gmail.com>
Maintainer: Zonglong Fan
Maintainer-email: <lazyboy.fan@gmail.com>
License: MIT
Platform: UNKNOWN
Requires-Python: >=2.7, <3.0
